README.rst
setup.py
PyBoard.egg-info/PKG-INFO
PyBoard.egg-info/SOURCES.txt
PyBoard.egg-info/dependency_links.txt
PyBoard.egg-info/not-zip-safe
PyBoard.egg-info/requires.txt
PyBoard.egg-info/top_level.txt
pyboard/__init__.py
pyboard/board.py
pyboard/main.py
pyboard/pyboard_constants.py
pyboard/pyboard_core.py
pyboard/pyboard_iot.py